fxy/__init__.py
fxy/lib.py
fxy/model.py
fxy/nlp2vec.py
openfxy-0.1.4.dist-info/LICENSE
openfxy-0.1.4.dist-info/METADATA
openfxy-0.1.4.dist-info/WHEEL
openfxy-0.1.4.dist-info/top_level.txt
openfxy-0.1.4.dist-info/RECORD
