Metadata-Version: 2.1
Name: openfxy
Version: 0.1.4
Summary: Security-Scenes-Feature-Engineering-Toolkit, Continuous Integration. 
Home-page: https://github.com/404notf0und/FXY
Author: 404 Not Found
Author-email: root@4o4notfound.org
License: MIT License
Platform: UNKNOWN
Requires-Python: >=3
Requires-Dist: numpy (==1.19.0)
Requires-Dist: pandas (==0.23.4)
Requires-Dist: scikit-learn (==0.23.1)
Requires-Dist: keras (==2.3.1)
Requires-Dist: keras-applications (==1.0.8)
Requires-Dist: keras-preprocessing (==1.1.0)
Requires-Dist: tensorflow (==2.0.0)
Requires-Dist: tensorflow-estimator (==2.0.0)
Requires-Dist: nltk (==3.5)
Requires-Dist: gensim (==3.8.1)
Requires-Dist: requests (==2.22.0)
Requires-Dist: scipy (==1.4.1)
